figuralib/__init__.py
figuralib/material_properties.py
figuralib/units.py
figuralib/figure_physics/__init__.py
figuralib/figure_physics/dynamics.py
figuralib/figure_physics/energy.py
figuralib/figure_physics/forces.py
figuralib/figure_physics/gravity.py
figuralib/figure_physics/kinematics.py
figuralib/figure_physics/momentum.py
figuralib/geometric_solids/__init__.py
figuralib/geometric_solids/cone.py
figuralib/geometric_solids/cube.py
figuralib/geometric_solids/cuboid.py
figuralib/geometric_solids/cylinder.py
figuralib/geometric_solids/prism.py
figuralib/geometric_solids/pyramid.py
figuralib/geometric_solids/sphere.py
figuralib/geometric_solids/torus.py
figuralib/plane_metrics/__init__.py
figuralib/plane_metrics/circle.py
figuralib/plane_metrics/ellipse.py
figuralib/plane_metrics/parallelogram.py
figuralib/plane_metrics/polygon.py
figuralib/plane_metrics/quadrilateral.py
figuralib/plane_metrics/rectangle.py
figuralib/plane_metrics/trapezoid.py
figuralib/plane_metrics/triangle.py
figuralib-0.0.2.dist-info/LICENSE
figuralib-0.0.2.dist-info/METADATA
figuralib-0.0.2.dist-info/WHEEL
figuralib-0.0.2.dist-info/top_level.txt
figuralib-0.0.2.dist-info/RECORD
