Metadata-Version: 2.1
Name: figuralib
Version: 0.0.2
Summary: With FiguraLib you can calculate figures, surfaces and physics.
Author: Julian Hess
Project-URL: GitHub, https://github.com/julian-hess/FiguraLib.git
Project-URL: Dokumentation, https://github.com/julian-hess/FiguraLib/blob/Files/documentation.md
Classifier: Programming Language :: Python :: 3.11
Classifier: License :: OSI Approved :: MIT License
Classifier: Operating System :: OS Independent
Classifier: Intended Audience :: Developers
License-File: LICENSE
